README.rst
nc-negotiate
proxy-negotiate
proxy_negotiate.py
setup.py
Proxy_Negotiate.egg-info/PKG-INFO
Proxy_Negotiate.egg-info/SOURCES.txt
Proxy_Negotiate.egg-info/dependency_links.txt
Proxy_Negotiate.egg-info/requires.txt
Proxy_Negotiate.egg-info/top_level.txt