Metadata-Version: 1.1
Name: Proxy-Negotiate
Version: 1.0.0
Summary: HTTP Negotiate proxy authentication support for applications.
Home-page: https://github.com/cour4g3/proxy-negotiate
Author: Michael de Villiers
Author-email: michael@cour4g3.me
License: MIT
Platform: any
Classifier: Environment :: Console
Classifier: Intended Audience :: System Administrators
Classifier: License :: OSI Approved :: MIT License
Classifier: Operating System :: OS Independent
Classifier: Programming Language :: Python :: 2.6
Classifier: Programming Language :: Python :: 2.7
Classifier: Programming Language :: Python :: 3.3
Classifier: Programming Language :: Python :: 3.4
Classifier: Programming Language :: Python :: 3.5
Classifier: Topic :: Internet :: Proxy Servers
Classifier: Topic :: Security
Classifier: Topic :: System :: Systems Administration :: Authentication/Directory
Classifier: Topic :: Utilities
